cryptocurreciestools/__init__.py
cryptocurreciestools/dataset.py
cryptocurrenciestools/__init__.py
cryptocurrenciestools/dataset.py
cryptocurrenciestools-0.3.dev0.dist-info/DESCRIPTION.rst
cryptocurrenciestools-0.3.dev0.dist-info/METADATA
cryptocurrenciestools-0.3.dev0.dist-info/RECORD
cryptocurrenciestools-0.3.dev0.dist-info/WHEEL
cryptocurrenciestools-0.3.dev0.dist-info/metadata.json
cryptocurrenciestools-0.3.dev0.dist-info/top_level.txt
