Metadata-Version: 2.0
Name: cryptocurrenciestools
Version: 0.3.dev0
Summary: Download and analyse cryptocurrencies data
Home-page: https://github.com/mohamedamjad/CMC_data_sniffer
Author: Mohamed Amjad LASRI
Author-email: amjad.sig@gmail.com
License: UNKNOWN
Download-URL: https://github.com/mohamedamjad/CMC_data_sniffer/archive/0.3dev.tar.gz
Keywords: cryptocurrency,analysis,tools,bitcoin,data
Platform: UNKNOWN
Classifier: Development Status :: 3 - Alpha
Requires-Python: >=2.6
Requires-Dist: pandas
Requires-Dist: requests
